{
            "sigma": {
                "bounds" : {
                    "lower" : 0.0,
                    "upper" : 1.0
                },
                "distribution" : "uniform",
                "default" : 0.0
            },
            "tau_s": {
                "bounds" : {
                    "lower" : 0.0,
                    "upper" : 1.0
                },
                "distribution" : "uniform",
                "default" : 0.02
            },
            "tau_m": {
                "bounds" : {
                    "lower" : 0.0,
                    "upper" : 1.0
                },
                "distribution" : "uniform",
                "default" : 0.02
            },
            "C_m": {
                "bounds" : {
                    "lower" : 0.0,
                    "upper" : 1.0
                },
                "distribution" : "uniform",
                "default" : 0.02
            },
            "J_E": {
                "bounds" : {
                    "lower" : 0.0,
                    "upper" : 1.0
                },
                "distribution" : "uniform",
                "default" : 0.02
            },
}